easyfacenet/__init__.py
easyfacenet/contributed/__init__.py
easyfacenet/contributed/batch_represent.py
easyfacenet/contributed/cluster.py
easyfacenet/contributed/clustering.py
easyfacenet/contributed/export_embeddings.py
easyfacenet/contributed/face.py
easyfacenet/contributed/predict.py
easyfacenet/contributed/real_time_face_recognition.py
easyfacenet/simple/__init__.py
easyfacenet/simple/download_model.py
easyfacenet/simple/facenet.py
easyfacenet/src/__init__.py
easyfacenet/src/calculate_filtering_metrics.py
easyfacenet/src/classifier.py
easyfacenet/src/compare.py
easyfacenet/src/decode_msceleb_dataset.py
easyfacenet/src/download_and_extract.py
easyfacenet/src/facenet.py
easyfacenet/src/freeze_graph.py
easyfacenet/src/lfw.py
easyfacenet/src/train_softmax.py
easyfacenet/src/train_tripletloss.py
easyfacenet/src/validate_on_lfw.py
easyfacenet/src/align/__init__.py
easyfacenet/src/align/align_dataset_mtcnn.py
easyfacenet/src/align/det1.npy
easyfacenet/src/align/det2.npy
easyfacenet/src/align/det3.npy
easyfacenet/src/align/detect_face.py
easyfacenet/src/generative/__init__.py
easyfacenet/src/generative/calculate_attribute_vectors.py
easyfacenet/src/generative/modify_attribute.py
easyfacenet/src/generative/train_vae.py
easyfacenet/src/generative/models/__init__.py
easyfacenet/src/generative/models/dfc_vae.py
easyfacenet/src/generative/models/dfc_vae_large.py
easyfacenet/src/generative/models/dfc_vae_resnet.py
easyfacenet/src/generative/models/vae_base.py
easyfacenet/src/models/__init__.py
easyfacenet/src/models/dummy.py
easyfacenet/src/models/inception_resnet_v1.py
easyfacenet/src/models/inception_resnet_v2.py
easyfacenet/src/models/squeezenet.py
easyfacenet/tmp/__init__.py
easyfacenet/tmp/align_dataset.py
easyfacenet/tmp/align_dlib.py
easyfacenet/tmp/cacd2000_split_identities.py
easyfacenet/tmp/dataset_read_speed.py
easyfacenet/tmp/deepdream.py
easyfacenet/tmp/download_vgg_face_dataset.py
easyfacenet-1.0.5.dist-info/METADATA
easyfacenet-1.0.5.dist-info/RECORD
easyfacenet-1.0.5.dist-info/WHEEL
easyfacenet-1.0.5.dist-info/top_level.txt
